docaligner/__init__.py
docaligner/aligner.py
docaligner/heatmap_reg/__init__.py
docaligner/heatmap_reg/infer.py
docaligner/heatmap_reg/ckpt/README.md
docaligner/point_reg/__init__.py
docaligner/point_reg/infer.py
docaligner/point_reg/ckpt/README.md
docaligner_docsaid-1.1.1.dist-info/licenses/LICENSE
docaligner_docsaid-1.1.1.dist-info/METADATA
docaligner_docsaid-1.1.1.dist-info/WHEEL
docaligner_docsaid-1.1.1.dist-info/top_level.txt
docaligner_docsaid-1.1.1.dist-info/RECORD
